[
  {
    "spot_id": "A01",
    "hexagon": [
      [
        501,
        2360
      ],
      [
        501,
        2494
      ],
      [
        750,
        2596
      ],
      [
        992,
        2537
      ],
      [
        994,
        2403
      ],
      [
        744,
        2332
      ]
    ]
  },
  {
    "spot_id": "A02",
    "hexagon": [
      [
        738,
        2331
      ],
      [
        739,
        2451
      ],
      [
        993,
        2534
      ],
      [
        1185,
        2494
      ],
      [
        1188,
        2371
      ],
      [
        970,
        2310
      ]
    ]
  },
  {
    "spot_id": "A03",
    "hexagon": [
      [
        978,
        2278
      ],
      [
        972,
        2406
      ],
      [
        1253,
        2489
      ],
      [
        1415,
        2444
      ],
      [
        1412,
        2330
      ],
      [
        1171,
        2250
      ]
    ]
  },
  {
    "spot_id": "A04",
    "hexagon": [
      [
        1261,
        2204
      ],
      [
        1266,
        2351
      ],
      [
        1442,
        2442
      ],
      [
        1628,
        2390
      ],
      [
        1628,
        2247
      ],
      [
        1428,
        2175
      ]
    ]
  },
  {
    "spot_id": "A05",
    "hexagon": [
      [
        1447,
        2166
      ],
      [
        1452,
        2313
      ],
      [
        1652,
        2418
      ],
      [
        1847,
        2375
      ],
      [
        1837,
        2242
      ],
      [
        1637,
        2147
      ]
    ]
  },
  {
    "spot_id": "A06",
    "hexagon": [
      [
        1637,
        2123
      ],
      [
        1633,
        2285
      ],
      [
        1847,
        2375
      ],
      [
        2028,
        2332
      ],
      [
        2028,
        2199
      ],
      [
        1823,
        2094
      ]
    ]
  },
  {
    "spot_id": "A07",
    "hexagon": [
      [
        1847,
        2104
      ],
      [
        1852,
        2256
      ],
      [
        2042,
        2337
      ],
      [
        2180,
        2304
      ],
      [
        2175,
        2166
      ],
      [
        1975,
        2090
      ]
    ]
  },
  {
    "spot_id": "A08",
    "hexagon": [
      [
        2042,
        2104
      ],
      [
        2052,
        2228
      ],
      [
        2185,
        2280
      ],
      [
        2332,
        2256
      ],
      [
        2332,
        2175
      ],
      [
        2152,
        2099
      ]
    ]
  },
  {
    "spot_id": "A09",
    "hexagon": [
      [
        2175,
        2071
      ],
      [
        2194,
        2213
      ],
      [
        2390,
        2271
      ],
      [
        2523,
        2251
      ],
      [
        2513,
        2142
      ],
      [
        2323,
        2052
      ]
    ]
  },
  {
    "spot_id": "A10",
    "hexagon": [
      [
        2354,
        2062
      ],
      [
        2351,
        2166
      ],
      [
        2565,
        2230
      ],
      [
        2685,
        2201
      ],
      [
        2684,
        2124
      ],
      [
        2475,
        2044
      ]
    ]
  },
  {
    "spot_id": "A11",
    "hexagon": [
      [
        2504,
        2013
      ],
      [
        2509,
        2128
      ],
      [
        2689,
        2180
      ],
      [
        2818,
        2156
      ],
      [
        2799,
        2075
      ],
      [
        2623,
        1999
      ]
    ]
  },
  {
    "spot_id": "A12",
    "hexagon": [
      [
        2670,
        1990
      ],
      [
        2675,
        2099
      ],
      [
        2856,
        2180
      ],
      [
        2956,
        2152
      ],
      [
        2942,
        2037
      ],
      [
        2775,
        1966
      ]
    ]
  },
  {
    "spot_id": "A13",
    "hexagon": [
      [
        2818,
        1975
      ],
      [
        2818,
        2080
      ],
      [
        2985,
        2152
      ],
      [
        3094,
        2118
      ],
      [
        3089,
        2052
      ],
      [
        2908,
        1952
      ]
    ]
  },
  {
    "spot_id": "A14",
    "hexagon": [
      [
        2937,
        1947
      ],
      [
        2937,
        2061
      ],
      [
        3094,
        2109
      ],
      [
        3237,
        2061
      ],
      [
        3237,
        1999
      ],
      [
        3051,
        1928
      ]
    ]
  },
  {
    "spot_id": "A15",
    "hexagon": [
      [
        769,
        2444
      ],
      [
        769,
        2593
      ],
      [
        1056,
        2716
      ],
      [
        1303,
        2653
      ],
      [
        1305,
        2502
      ],
      [
        1025,
        2420
      ]
    ]
  },
  {
    "spot_id": "A16",
    "hexagon": [
      [
        1009,
        2375
      ],
      [
        1014,
        2547
      ],
      [
        1319,
        2666
      ],
      [
        1547,
        2608
      ],
      [
        1528,
        2418
      ],
      [
        1295,
        2318
      ]
    ]
  },
  {
    "spot_id": "A17",
    "hexagon": [
      [
        1342,
        2328
      ],
      [
        1333,
        2504
      ],
      [
        1561,
        2608
      ],
      [
        1780,
        2551
      ],
      [
        1752,
        2394
      ],
      [
        1476,
        2294
      ]
    ]
  },
  {
    "spot_id": "A18",
    "hexagon": [
      [
        1576,
        2328
      ],
      [
        1561,
        2470
      ],
      [
        1775,
        2556
      ],
      [
        1971,
        2513
      ],
      [
        1966,
        2390
      ],
      [
        1747,
        2299
      ]
    ]
  },
  {
    "spot_id": "A19",
    "hexagon": [
      [
        1714,
        2290
      ],
      [
        1709,
        2423
      ],
      [
        1975,
        2513
      ],
      [
        2185,
        2470
      ],
      [
        2175,
        2342
      ],
      [
        1885,
        2247
      ]
    ]
  },
  {
    "spot_id": "A20",
    "hexagon": [
      [
        1890,
        2242
      ],
      [
        1890,
        2375
      ],
      [
        2180,
        2475
      ],
      [
        2370,
        2423
      ],
      [
        2366,
        2266
      ],
      [
        2080,
        2199
      ]
    ]
  },
  {
    "spot_id": "A21",
    "hexagon": [
      [
        2080,
        2190
      ],
      [
        2080,
        2332
      ],
      [
        2366,
        2423
      ],
      [
        2556,
        2385
      ],
      [
        2547,
        2251
      ],
      [
        2261,
        2166
      ]
    ]
  },
  {
    "spot_id": "A22",
    "hexagon": [
      [
        2323,
        2166
      ],
      [
        2323,
        2318
      ],
      [
        2566,
        2394
      ],
      [
        2727,
        2356
      ],
      [
        2723,
        2237
      ],
      [
        2480,
        2137
      ]
    ]
  },
  {
    "spot_id": "A23",
    "hexagon": [
      [
        2439,
        2161
      ],
      [
        2439,
        2278
      ],
      [
        2732,
        2353
      ],
      [
        2898,
        2316
      ],
      [
        2899,
        2201
      ],
      [
        2590,
        2125
      ]
    ]
  },
  {
    "spot_id": "A24",
    "hexagon": [
      [
        2591,
        2120
      ],
      [
        2594,
        2243
      ],
      [
        2898,
        2316
      ],
      [
        3036,
        2280
      ],
      [
        3035,
        2187
      ],
      [
        2738,
        2109
      ]
    ]
  },
  {
    "spot_id": "A25",
    "hexagon": [
      [
        2792,
        2113
      ],
      [
        2791,
        2205
      ],
      [
        3036,
        2281
      ],
      [
        3174,
        2247
      ],
      [
        3178,
        2162
      ],
      [
        2901,
        2098
      ]
    ]
  },
  {
    "spot_id": "A26",
    "hexagon": [
      [
        2898,
        2060
      ],
      [
        2899,
        2183
      ],
      [
        3179,
        2246
      ],
      [
        3340,
        2215
      ],
      [
        3340,
        2112
      ],
      [
        3028,
        2056
      ]
    ]
  },
  {
    "spot_id": "A27",
    "hexagon": [
      [
        3033,
        2036
      ],
      [
        3030,
        2152
      ],
      [
        3343,
        2213
      ],
      [
        3464,
        2177
      ],
      [
        3460,
        2068
      ],
      [
        3184,
        2019
      ]
    ]
  },
  {
    "spot_id": "A28",
    "hexagon": [
      [
        3247,
        2020
      ],
      [
        3243,
        2115
      ],
      [
        3474,
        2186
      ],
      [
        3608,
        2158
      ],
      [
        3605,
        2064
      ],
      [
        3390,
        2006
      ]
    ]
  },
  {
    "spot_id": "A29",
    "hexagon": [
      [
        3354,
        1987
      ],
      [
        3354,
        2085
      ],
      [
        3614,
        2163
      ],
      [
        3738,
        2139
      ],
      [
        3734,
        2045
      ],
      [
        3503,
        1975
      ]
    ]
  }
]